{
  "title": "What does it mean to be creative?",
  "backlink": "https://www.reddit.com/r/Art/comments/htd8dm/what_does_it_mean_to_be_creative/",
  "language": "en",
  "classifications": [
    "reddit post"
  ],
  "properties": {
    "author": "DumbTerminaI",
    "publication_year": 2024,
    "external_link": "https://www.reddit.com/r/Art/comments/htd8dm/what_does_it_mean_to_be_creative/",
    "sentiment_score": "0.9724",
    "sentiment_label": "very positive",
    "sentiment_scope": "Title & text content"
  }
}