{
  "title": "Is there any technology utilizing the strong and/or weak forces?",
  "backlink": "https://www.reddit.com/r/askscience/comments/hmt6a/is_there_any_technology_utilizing_the_strong/",
  "language": "en",
  "classifications": [
    "reddit post"
  ],
  "properties": {
    "author": "econleech",
    "publication_year": 2024,
    "external_link": "https://www.reddit.com/r/askscience/comments/hmt6a/is_there_any_technology_utilizing_the_strong/",
    "sentiment_score": "0.327",
    "sentiment_label": "positive",
    "sentiment_scope": "Title & text content"
  }
}