{
  "title": "Are there any other viable power sources available to us other than electromagnetic induction and photovoltaic technology?",
  "backlink": "https://www.reddit.com/r/askscience/comments/9d5v83/are_there_any_other_viable_power_sources/",
  "language": "en",
  "classifications": [
    "reddit post"
  ],
  "properties": {
    "author": "Capernici",
    "publication_year": 2024,
    "external_link": "https://www.reddit.com/r/askscience/comments/9d5v83/are_there_any_other_viable_power_sources/",
    "sentiment_score": "-0.3939",
    "sentiment_label": "negative",
    "sentiment_scope": "Title & text content"
  }
}