{
  "title": "Does storage technology have an upper limit?",
  "backlink": "https://www.reddit.com/r/askscience/comments/5htrw2/does_storage_technology_have_an_upper_limit/",
  "language": "en",
  "classifications": [
    "reddit post"
  ],
  "properties": {
    "author": "CaptainVonDanDan",
    "publication_year": 2024,
    "external_link": "https://www.reddit.com/r/askscience/comments/5htrw2/does_storage_technology_have_an_upper_limit/",
    "sentiment_score": "0.3939",
    "sentiment_label": "positive",
    "sentiment_scope": "Title & text content"
  }
}