{
  "title": "Is there a literary equivalent to \"outsider art\"?",
  "backlink": "https://www.reddit.com/r/books/comments/17kvyok/is_there_a_literary_equivalent_to_outsider_art/",
  "language": "en",
  "classifications": [
    "reddit post"
  ],
  "properties": {
    "author": "zzzzzzzzzra",
    "publication_year": 2024,
    "external_link": "https://www.reddit.com/r/books/comments/17kvyok/is_there_a_literary_equivalent_to_outsider_art/",
    "sentiment_score": "0.3919",
    "sentiment_label": "positive",
    "sentiment_scope": "Title & text content"
  }
}