{
  "title": "I accidentally bought almond extract instead of vanilla extract and, holy shit, it’s so delicious.",
  "backlink": "https://www.reddit.com/r/Cooking/comments/imuae1/i_accidentally_bought_almond_extract_instead_of/",
  "language": "en",
  "classifications": [
    "reddit post"
  ],
  "properties": {
    "author": "PoopMobile9000",
    "publication_year": 2024,
    "external_link": "https://www.reddit.com/r/Cooking/comments/imuae1/i_accidentally_bought_almond_extract_instead_of/",
    "sentiment_score": "0.9831",
    "sentiment_label": "very positive",
    "sentiment_scope": "Title & text content"
  }
}