{
  "title": "Tonight I made a delicious shrimp scampi.",
  "backlink": "https://www.reddit.com/r/Cooking/comments/18u42rs/tonight_i_made_a_delicious_shrimp_scampi/",
  "language": "en",
  "classifications": [
    "reddit post"
  ],
  "properties": {
    "author": "EmilyamI",
    "publication_year": 2024,
    "external_link": "https://www.reddit.com/r/Cooking/comments/18u42rs/tonight_i_made_a_delicious_shrimp_scampi/",
    "sentiment_score": "0.5106",
    "sentiment_label": "very positive",
    "sentiment_scope": "Title & text content"
  }
}