{
  "title": "What's your favorite low-effort food that feels super sophisticated?",
  "backlink": "https://www.reddit.com/r/Cooking/comments/14o1rly/whats_your_favorite_loweffort_food_that_feels/",
  "language": "en",
  "classifications": [
    "reddit post"
  ],
  "properties": {
    "author": "lemonFiend",
    "publication_year": 2024,
    "external_link": "https://www.reddit.com/r/Cooking/comments/14o1rly/whats_your_favorite_loweffort_food_that_feels/",
    "sentiment_score": "0.9618",
    "sentiment_label": "very positive",
    "sentiment_scope": "Title & text content"
  }
}