{
  "title": "Your MOST elite, delicious, to die for pan sauce to go with roast chicken??",
  "backlink": "https://www.reddit.com/r/Cooking/comments/18g92xf/your_most_elite_delicious_to_die_for_pan_sauce_to/",
  "language": "en",
  "classifications": [
    "reddit post"
  ],
  "properties": {
    "author": "pfemme2",
    "publication_year": 2024,
    "external_link": "https://www.reddit.com/r/Cooking/comments/18g92xf/your_most_elite_delicious_to_die_for_pan_sauce_to/",
    "sentiment_score": "0.9832",
    "sentiment_label": "very positive",
    "sentiment_scope": "Title & text content"
  }
}