{
  "title": "Creativity has to go beyond aesthetics and proactively merge with tech & biz, to create enough job opportunities in a fast-changing Tech world",
  "backlink": "/r/doodlingo/comments/15l9o0p/redefining_creativity_in_the_modern_age/",
  "language": "en",
  "classifications": [
    "reddit post"
  ],
  "properties": {
    "author": "AkritiJha",
    "publication_year": 2024,
    "external_link": "/r/doodlingo/comments/15l9o0p/redefining_creativity_in_the_modern_age/",
    "sentiment_score": "0.743",
    "sentiment_label": "very positive",
    "sentiment_scope": "Title content only"
  }
}