{
  "title": "How to foster creativity (during pandemic!)",
  "backlink": "https://www.reddit.com/r/Design/comments/mwqiwg/how_to_foster_creativity_during_pandemic/",
  "language": "en",
  "classifications": [
    "reddit post"
  ],
  "properties": {
    "author": "Brilliant-Spend-2083",
    "publication_year": 2024,
    "external_link": "https://www.reddit.com/r/Design/comments/mwqiwg/how_to_foster_creativity_during_pandemic/",
    "sentiment_score": "0.9885",
    "sentiment_label": "very positive",
    "sentiment_scope": "Title & text content"
  }
}