{
  "title": "Collaborate in young artists' creative project!",
  "backlink": "https://www.reddit.com/r/Design/comments/jvwmc9/collaborate_in_young_artists_creative_project/",
  "language": "en",
  "classifications": [
    "reddit post"
  ],
  "properties": {
    "author": "bbeeaa",
    "publication_year": 2024,
    "external_link": "https://www.reddit.com/r/Design/comments/jvwmc9/collaborate_in_young_artists_creative_project/",
    "sentiment_score": "0.9841",
    "sentiment_label": "very positive",
    "sentiment_scope": "Title & text content"
  }
}