{
  "title": "Help needed on how to lay the tubes for an automatic watering plant system. I'm gonna build an automatic watering system for my plants. Lets say I've 20 plants whose water requirements will be varying . I'm planning to use my 20l water can as the tank.",
  "backlink": "https://www.reddit.com/r/DIY/comments/13i67t3/help_needed_on_how_to_lay_the_tubes_for_an/",
  "language": "en",
  "classifications": [
    "reddit post"
  ],
  "properties": {
    "author": "dreamer881",
    "publication_year": 2024,
    "external_link": "https://www.reddit.com/r/DIY/comments/13i67t3/help_needed_on_how_to_lay_the_tubes_for_an/",
    "sentiment_score": "0.6136",
    "sentiment_label": "very positive",
    "sentiment_scope": "Title & text content"
  }
}