{
  "title": "What North Koreans Think of America [Full] (2017). Really fascinating insight into a typical North Koreans views on Americans",
  "backlink": "https://m.youtube.com/watch?feature=share&v=YXo-Vov_98Y",
  "language": "en",
  "classifications": [
    "reddit post"
  ],
  "properties": {
    "author": "EhAhKen",
    "publication_year": 2024,
    "external_link": "https://m.youtube.com/watch?feature=share&v=YXo-Vov_98Y",
    "sentiment_score": "0.5849",
    "sentiment_label": "very positive",
    "sentiment_scope": "Title content only"
  }
}