{
  "title": "Achievement and embarrassment unlocked",
  "backlink": "https://www.reddit.com/r/Fitness/comments/ojccj/achievement_and_embarrassment_unlocked/",
  "language": "en",
  "classifications": [
    "reddit post"
  ],
  "properties": {
    "author": "spinozasrobot",
    "publication_year": 2024,
    "external_link": "https://www.reddit.com/r/Fitness/comments/ojccj/achievement_and_embarrassment_unlocked/",
    "sentiment_score": "-0.9135",
    "sentiment_label": "very negative",
    "sentiment_scope": "Title & text content"
  }
}