{
  "title": "Any health benefit to using the sauna after a workout?",
  "backlink": "https://www.reddit.com/r/Fitness/comments/2sdc8o/any_health_benefit_to_using_the_sauna_after_a/",
  "language": "en",
  "classifications": [
    "reddit post"
  ],
  "properties": {
    "author": "Badgers1111",
    "publication_year": 2024,
    "external_link": "https://www.reddit.com/r/Fitness/comments/2sdc8o/any_health_benefit_to_using_the_sauna_after_a/",
    "sentiment_score": "0.829",
    "sentiment_label": "very positive",
    "sentiment_scope": "Title & text content"
  }
}