{
  "title": "Workout and motivation tips for Obese College student?\n ",
  "backlink": "https://www.reddit.com/r/Fitness/comments/90yao/workout_and_motivation_tips_for_obese_college/",
  "language": "en",
  "classifications": [
    "reddit post"
  ],
  "properties": {
    "author": "randomcharacters123",
    "publication_year": 2024,
    "external_link": "https://www.reddit.com/r/Fitness/comments/90yao/workout_and_motivation_tips_for_obese_college/",
    "sentiment_score": "-0.7174",
    "sentiment_label": "very negative",
    "sentiment_scope": "Title & text content"
  }
}