{
  "title": "My motivation at the gym today",
  "backlink": "https://www.reddit.com/r/Fitness/comments/1opkcd/my_motivation_at_the_gym_today/",
  "language": "en",
  "classifications": [
    "reddit post"
  ],
  "properties": {
    "author": "Pulvercity",
    "publication_year": 2024,
    "external_link": "https://www.reddit.com/r/Fitness/comments/1opkcd/my_motivation_at_the_gym_today/",
    "sentiment_score": "0.8656",
    "sentiment_label": "very positive",
    "sentiment_scope": "Title & text content"
  }
}