{
  "title": "Achieve Total Wellness With Foxboro MA Chiropractor",
  "backlink": "https://www.reddit.com/r/Fitness/comments/618ib9/achieve_total_wellness_with_foxboro_ma/",
  "language": "en",
  "classifications": [
    "reddit post"
  ],
  "properties": {
    "author": "stainsted",
    "publication_year": 2024,
    "external_link": "https://www.reddit.com/r/Fitness/comments/618ib9/achieve_total_wellness_with_foxboro_ma/",
    "sentiment_score": "-0.9175",
    "sentiment_label": "very negative",
    "sentiment_scope": "Title & text content"
  }
}