{
  "title": "Newly found motivation...Running to Military cadence tracks.",
  "backlink": "https://www.reddit.com/r/Fitness/comments/2x8tlw/newly_found_motivationrunning_to_military_cadence/",
  "language": "en",
  "classifications": [
    "reddit post"
  ],
  "properties": {
    "author": "urbngrd",
    "publication_year": 2024,
    "external_link": "https://www.reddit.com/r/Fitness/comments/2x8tlw/newly_found_motivationrunning_to_military_cadence/",
    "sentiment_score": "-0.2452",
    "sentiment_label": "negative",
    "sentiment_scope": "Title & text content"
  }
}