{
  "title": "Top 10 Health and Longevity Innovations in 2020",
  "backlink": "https://www.gowinglife.com/top-10-health-and-longevity-innovations-in-2020/",
  "language": "en",
  "classifications": [
    "reddit post"
  ],
  "properties": {
    "author": "aviroy",
    "publication_year": 2024,
    "external_link": "https://www.gowinglife.com/top-10-health-and-longevity-innovations-in-2020/",
    "sentiment_score": "0.2023",
    "sentiment_label": "positive",
    "sentiment_scope": "Title content only"
  }
}