{
  "title": "Final Fantasy VII strategy guide",
  "backlink": "https://www.reddit.com/r/gaming/comments/1542u1g/final_fantasy_vii_strategy_guide/",
  "language": "en",
  "classifications": [
    "reddit post"
  ],
  "properties": {
    "author": "MaintenancePanda",
    "publication_year": 2024,
    "external_link": "https://www.reddit.com/r/gaming/comments/1542u1g/final_fantasy_vii_strategy_guide/",
    "sentiment_score": "0.9514",
    "sentiment_label": "very positive",
    "sentiment_scope": "Title & text content"
  }
}