{
  "title": "Military strategy game, tips?",
  "backlink": "https://www.reddit.com/r/gaming/comments/t0juwz/military_strategy_game_tips/",
  "language": "en",
  "classifications": [
    "reddit post"
  ],
  "properties": {
    "author": "williepep1960",
    "publication_year": 2024,
    "external_link": "https://www.reddit.com/r/gaming/comments/t0juwz/military_strategy_game_tips/",
    "sentiment_score": "0.9072",
    "sentiment_label": "very positive",
    "sentiment_scope": "Title & text content"
  }
}