{
  "title": "You love gaming but you don't get excited about new releases",
  "backlink": "https://www.reddit.com/r/gaming/comments/186yppw/you_love_gaming_but_you_dont_get_excited_about/",
  "language": "en",
  "classifications": [
    "reddit post"
  ],
  "properties": {
    "author": "kraydful",
    "publication_year": 2024,
    "external_link": "https://www.reddit.com/r/gaming/comments/186yppw/you_love_gaming_but_you_dont_get_excited_about/",
    "sentiment_score": "0.2373",
    "sentiment_label": "positive",
    "sentiment_scope": "Title & text content"
  }
}