{
  "title": "I'm really interested in the Cold War. What I don't understand is how it spread from Europe to the 3rd World yet ended in Berlin. Have any recommended reading or general insight?",
  "backlink": "https://www.reddit.com/r/history/comments/sg2ya/im_really_interested_in_the_cold_war_what_i_dont/",
  "language": "en",
  "classifications": [
    "reddit post"
  ],
  "properties": {
    "author": "taxikab817",
    "publication_year": 2024,
    "external_link": "https://www.reddit.com/r/history/comments/sg2ya/im_really_interested_in_the_cold_war_what_i_dont/",
    "sentiment_score": "-0.0276",
    "sentiment_label": "neutral",
    "sentiment_scope": "Title content only"
  }
}