{
  "title": "Interview with Prof. Alexander Puzrin about his recent headline making paper on the Dyaltov Pass Incident (1959). He shares many of his insights, explains how they conducted their research and what it all means for one of the internet's favorite historical mysteries. (Podcast)",
  "backlink": "https://hauntedwalk.com/news/episode-100-dyatlov-pass-mystery-solved-part-two/",
  "language": "en",
  "classifications": [
    "reddit post"
  ],
  "properties": {
    "author": "TheHauntedWalk",
    "publication_year": 2024,
    "external_link": "https://hauntedwalk.com/news/episode-100-dyatlov-pass-mystery-solved-part-two/",
    "sentiment_score": "0.6369",
    "sentiment_label": "very positive",
    "sentiment_scope": "Title content only"
  }
}