{
  "title": "What are some highly debatable historical questions?",
  "backlink": "https://www.reddit.com/r/history/comments/3pfylx/what_are_some_highly_debatable_historical/",
  "language": "en",
  "classifications": [
    "reddit post"
  ],
  "properties": {
    "author": "bashybee",
    "publication_year": 2024,
    "external_link": "https://www.reddit.com/r/history/comments/3pfylx/what_are_some_highly_debatable_historical/",
    "sentiment_score": "0.4939",
    "sentiment_label": "positive",
    "sentiment_scope": "Title & text content"
  }
}