{
  "title": "TBH The CGI Rachel from Blade Runner 2049 is still the best de-aging in cinema",
  "backlink": "https://www.reddit.com/r/movies/comments/14vumw6/tbh_the_cgi_rachel_from_blade_runner_2049_is/",
  "language": "en",
  "classifications": [
    "reddit post"
  ],
  "properties": {
    "author": "SitriHyo",
    "publication_year": 2024,
    "external_link": "https://www.reddit.com/r/movies/comments/14vumw6/tbh_the_cgi_rachel_from_blade_runner_2049_is/",
    "sentiment_score": "0.9474",
    "sentiment_label": "very positive",
    "sentiment_scope": "Title & text content"
  }
}