{
  "title": "John Wick 4 has Bill Skarsgard wear the best suits in cinema, AFAIK, what other movies or actors have worn outfits as good?",
  "backlink": "https://www.reddit.com/r/movies/comments/17lykxr/john_wick_4_has_bill_skarsgard_wear_the_best/",
  "language": "en",
  "classifications": [
    "reddit post"
  ],
  "properties": {
    "author": "Flares117",
    "publication_year": 2024,
    "external_link": "https://www.reddit.com/r/movies/comments/17lykxr/john_wick_4_has_bill_skarsgard_wear_the_best/",
    "sentiment_score": "0.8611",
    "sentiment_label": "very positive",
    "sentiment_scope": "Title & text content"
  }
}