{
  "title": "Andy Serkis to Receive Special Honor at 2020 BAFTAs for Outstanding Contribution to Cinema",
  "backlink": "https://www.screendaily.com/news/andy-serkis-to-receive-bafta-for-outstanding-contribution-to-cinema/5146434.article",
  "language": "en",
  "classifications": [
    "reddit post"
  ],
  "properties": {
    "author": "BunyipPouch",
    "publication_year": 2024,
    "external_link": "https://www.screendaily.com/news/andy-serkis-to-receive-bafta-for-outstanding-contribution-to-cinema/5146434.article",
    "sentiment_score": "0.872",
    "sentiment_label": "very positive",
    "sentiment_scope": "Title content only"
  }
}