{
  "title": "id like some actual critique on \"Snow on tha Bluff\"",
  "backlink": "https://www.reddit.com/r/movies/comments/1r1l9r/id_like_some_actual_critique_on_snow_on_tha_bluff/",
  "language": "en",
  "classifications": [
    "reddit post"
  ],
  "properties": {
    "author": "gucci_flocka_flame",
    "publication_year": 2024,
    "external_link": "https://www.reddit.com/r/movies/comments/1r1l9r/id_like_some_actual_critique_on_snow_on_tha_bluff/",
    "sentiment_score": "0.7045",
    "sentiment_label": "very positive",
    "sentiment_scope": "Title & text content"
  }
}