{
  "title": "X6zt - Chasing Dreams (feat. Anthony Meyer) | ♫ Copyright Free Music [uplifting]",
  "backlink": "https://m.youtube.com/watch?v=GxGc9GTQ0kA&list=PLYLUCM5lMSCylYfqlrYyZMFXdxksgqzB9&index=1",
  "language": "en",
  "classifications": [
    "reddit post"
  ],
  "properties": {
    "author": "Free-Music-Library",
    "publication_year": 2024,
    "external_link": "https://m.youtube.com/watch?v=GxGc9GTQ0kA&list=PLYLUCM5lMSCylYfqlrYyZMFXdxksgqzB9&index=1",
    "sentiment_score": "0.7184",
    "sentiment_label": "very positive",
    "sentiment_scope": "Title content only"
  }
}