{
  "title": "Friday uplifting music S.O.S requsted!",
  "backlink": "https://www.reddit.com/r/Music/comments/70cguz/friday_uplifting_music_sos_requsted/",
  "language": "en",
  "classifications": [
    "reddit post"
  ],
  "properties": {
    "author": "AvensisToy",
    "publication_year": 2024,
    "external_link": "https://www.reddit.com/r/Music/comments/70cguz/friday_uplifting_music_sos_requsted/",
    "sentiment_score": "0.765",
    "sentiment_label": "very positive",
    "sentiment_scope": "Title & text content"
  }
}