{
  "title": "Scientists Film Hummingbirds Flying Through Waterfalls, And It's Beautiful And Genius",
  "backlink": "https://www.sciencealert.com/watch-the-genius-and-beautiful-way-hummingbirds-fly-through-waterfalls",
  "language": "en",
  "classifications": [
    "reddit post"
  ],
  "properties": {
    "author": "Sorin61",
    "publication_year": 2024,
    "external_link": "https://www.sciencealert.com/watch-the-genius-and-beautiful-way-hummingbirds-fly-through-waterfalls",
    "sentiment_score": "0.5994",
    "sentiment_label": "very positive",
    "sentiment_scope": "Title content only"
  }
}