{
  "title": "100 most beautiful places in the world in pictures!",
  "backlink": "http://www.youramazingplaces.com/the-100-most-beautiful-and-breathtaking-places-in-the-world-in-pictures-part-1/",
  "language": "en",
  "classifications": [
    "reddit post"
  ],
  "properties": {
    "author": "bucysh",
    "publication_year": 2024,
    "external_link": "http://www.youramazingplaces.com/the-100-most-beautiful-and-breathtaking-places-in-the-world-in-pictures-part-1/",
    "sentiment_score": "0.6689",
    "sentiment_label": "very positive",
    "sentiment_scope": "Title content only"
  }
}