{
  "title": "Former Google engineer breaks down interview problems he uses to screen candidates. Lots of good coding, algorithms, and interview tips.",
  "backlink": "https://medium.com/@alexgolec/google-interview-problems-ratio-finder-d7aa8bf201e3",
  "language": "en",
  "classifications": [
    "reddit post"
  ],
  "properties": {
    "author": "jfasi",
    "publication_year": 2024,
    "external_link": "https://medium.com/@alexgolec/google-interview-problems-ratio-finder-d7aa8bf201e3",
    "sentiment_score": "0.0516",
    "sentiment_label": "slightly positive",
    "sentiment_scope": "Title content only"
  }
}