{
  "title": "Why Microsoft has made developers horrified about coding for Windows 8",
  "backlink": "http://arstechnica.com/microsoft/news/2011/06/html5-centric-windows-8-leaves-microsoft-developers-horrified.ars",
  "language": "en",
  "classifications": [
    "reddit post"
  ],
  "properties": {
    "author": "mistawobin",
    "publication_year": 2024,
    "external_link": "http://arstechnica.com/microsoft/news/2011/06/html5-centric-windows-8-leaves-microsoft-developers-horrified.ars",
    "sentiment_score": "-0.5423",
    "sentiment_label": "very negative",
    "sentiment_scope": "Title content only"
  }
}