{
  "title": "I [31M] feel that my girlfriend [23F] isn't quite supportive enough",
  "backlink": "https://www.reddit.com/r/relationships/comments/cl6clx/i_31m_feel_that_my_girlfriend_23f_isnt_quite/",
  "language": "en",
  "classifications": [
    "reddit post"
  ],
  "properties": {
    "author": "TruthSeeker402",
    "publication_year": 2024,
    "external_link": "https://www.reddit.com/r/relationships/comments/cl6clx/i_31m_feel_that_my_girlfriend_23f_isnt_quite/",
    "sentiment_score": "-0.9884",
    "sentiment_label": "very negative",
    "sentiment_scope": "Title & text content"
  }
}