{
  "title": "Unemployed husband for 2 years. 31 [F] 38 [M]. How do you stay supportive and happy?",
  "backlink": "https://www.reddit.com/r/relationships/comments/r3855u/unemployed_husband_for_2_years_31_f_38_m_how_do/",
  "language": "en",
  "classifications": [
    "reddit post"
  ],
  "properties": {
    "author": "ReceptionFar890",
    "publication_year": 2024,
    "external_link": "https://www.reddit.com/r/relationships/comments/r3855u/unemployed_husband_for_2_years_31_f_38_m_how_do/",
    "sentiment_score": "-0.8548",
    "sentiment_label": "very negative",
    "sentiment_scope": "Title & text content"
  }
}