{
  "title": "My [27F] Husband [28M] is addicted to porn and has 0 interest in me. I've been supportive, but reached breaking point. What next step to care for my own mental well-being?",
  "backlink": "https://www.reddit.com/r/relationships/comments/8oomu5/my_27f_husband_28m_is_addicted_to_porn_and_has_0/",
  "language": "en",
  "classifications": [
    "reddit post"
  ],
  "properties": {
    "author": "GuerillaHug",
    "publication_year": 2024,
    "external_link": "https://www.reddit.com/r/relationships/comments/8oomu5/my_27f_husband_28m_is_addicted_to_porn_and_has_0/",
    "sentiment_score": "0.9993",
    "sentiment_label": "very positive",
    "sentiment_scope": "Title & text content"
  }
}