{
  "title": "Galileo confirmed as author of pseudonymous 17th century astronomy text | It's a biting rebuttal to a philosopher's ideas about the 1604 supernova (\"stella nova\").",
  "backlink": "https://arstechnica.com/science/2022/10/historian-galileo-wrote-a-17th-century-astronomy-treatise-under-pseudonym/",
  "language": "en",
  "classifications": [
    "reddit post"
  ],
  "properties": {
    "author": "mepper",
    "publication_year": 2024,
    "external_link": "https://arstechnica.com/science/2022/10/historian-galileo-wrote-a-17th-century-astronomy-treatise-under-pseudonym/",
    "sentiment_score": "0.0",
    "sentiment_label": "neutral",
    "sentiment_scope": "Title content only"
  }
}