{
  "title": "The advanced silicon chips on which the future depends are all made in Taiwan – here’s why that matters",
  "backlink": "https://www.theguardian.com/commentisfree/2023/oct/21/silicon-chips-taiwan-semiconductor-manufacturing-company-tsmc",
  "language": "en",
  "classifications": [
    "reddit post"
  ],
  "properties": {
    "author": "Currency_Cat",
    "publication_year": 2024,
    "external_link": "https://www.theguardian.com/commentisfree/2023/oct/21/silicon-chips-taiwan-semiconductor-manufacturing-company-tsmc",
    "sentiment_score": "0.2732",
    "sentiment_label": "positive",
    "sentiment_scope": "Title content only"
  }
}