{
  "title": "Scientists Create New Material Five Times Lighter and Four Times Stronger Than Steel",
  "backlink": "https://scitechdaily.com/scientists-create-new-material-five-times-lighter-and-four-times-stronger-than-steel/",
  "language": "en",
  "classifications": [
    "reddit post"
  ],
  "properties": {
    "author": "Sorin61",
    "publication_year": 2024,
    "external_link": "https://scitechdaily.com/scientists-create-new-material-five-times-lighter-and-four-times-stronger-than-steel/",
    "sentiment_score": "0.5719",
    "sentiment_label": "very positive",
    "sentiment_scope": "Title content only"
  }
}