{
  "title": "I'm Kevin Scott, Chief Technology Officer of Microsoft, author, woodworker, perpetual learner, and podcast host. Ask me anything about AI, software development, or what I think about the future of tech.",
  "backlink": "https://www.reddit.com/r/technology/comments/uz33f3/im_kevin_scott_chief_technology_officer_of/",
  "language": "en",
  "classifications": [
    "reddit post"
  ],
  "properties": {
    "author": "KevinScottMicrosoft",
    "publication_year": 2024,
    "external_link": "https://www.reddit.com/r/technology/comments/uz33f3/im_kevin_scott_chief_technology_officer_of/",
    "sentiment_score": "0.9866",
    "sentiment_label": "very positive",
    "sentiment_scope": "Title & text content"
  }
}