{
  "title": "TIL that the news copter reporter who followed OJ's \"slow speed chase\" is a transgender woman who was an innovator in news copter reporting, has some pretty controversial opinions, and threatened to send an interviewer home in an ambulance.",
  "backlink": "https://en.wikipedia.org/wiki/Zoey_Tur",
  "language": "en",
  "classifications": [
    "reddit post"
  ],
  "properties": {
    "author": "davidnik",
    "publication_year": 2024,
    "external_link": "https://en.wikipedia.org/wiki/Zoey_Tur",
    "sentiment_score": "-0.1531",
    "sentiment_label": "slightly negative",
    "sentiment_scope": "Title content only"
  }
}