{
  "title": "19 hour layover in Paris, should I leave and explore?",
  "backlink": "https://www.reddit.com/r/travel/comments/120a1b6/19_hour_layover_in_paris_should_i_leave_and/",
  "language": "en",
  "classifications": [
    "reddit post"
  ],
  "properties": {
    "author": "SadResolution8577",
    "publication_year": 2024,
    "external_link": "https://www.reddit.com/r/travel/comments/120a1b6/19_hour_layover_in_paris_should_i_leave_and/",
    "sentiment_score": "0.3939",
    "sentiment_label": "positive",
    "sentiment_scope": "Title & text content"
  }
}