{
  "title": "Gadventures Maldives Dhoni explorer! Recommended?",
  "backlink": "https://www.reddit.com/r/travel/comments/15eemuv/gadventures_maldives_dhoni_explorer_recommended/",
  "language": "en",
  "classifications": [
    "reddit post"
  ],
  "properties": {
    "author": "Busy-Tart5218",
    "publication_year": 2024,
    "external_link": "https://www.reddit.com/r/travel/comments/15eemuv/gadventures_maldives_dhoni_explorer_recommended/",
    "sentiment_score": "0.8932",
    "sentiment_label": "very positive",
    "sentiment_scope": "Title & text content"
  }
}