{
  "title": "Who else has wrestled with writing doubts like \"Can I really write?\" and won? Looking for inspiration and actually... seeking advice...",
  "backlink": "https://www.reddit.com/r/writing/comments/18v5qb9/who_else_has_wrestled_with_writing_doubts_like/",
  "language": "en",
  "classifications": [
    "reddit post"
  ],
  "properties": {
    "author": "Quirky_Breadfruit317",
    "publication_year": 2024,
    "external_link": "https://www.reddit.com/r/writing/comments/18v5qb9/who_else_has_wrestled_with_writing_doubts_like/",
    "sentiment_score": "0.9795",
    "sentiment_label": "very positive",
    "sentiment_scope": "Title & text content"
  }
}