{
  "title": "any books that got you into writing/inspire you to write?",
  "backlink": "https://www.reddit.com/r/writing/comments/18e7yrg/any_books_that_got_you_into_writinginspire_you_to/",
  "language": "en",
  "classifications": [
    "reddit post"
  ],
  "properties": {
    "author": "Previous-Stay-912",
    "publication_year": 2024,
    "external_link": "https://www.reddit.com/r/writing/comments/18e7yrg/any_books_that_got_you_into_writinginspire_you_to/",
    "sentiment_score": "0.9946",
    "sentiment_label": "very positive",
    "sentiment_scope": "Title & text content"
  }
}