{
  "title": "Biden: Putin has committed war crimes, charges justified",
  "backlink": "https://kyivindependent.com/news-feed/biden-putin-has-committed-war-crimes-charges-justified",
  "language": "en",
  "classifications": [
    "reddit post"
  ],
  "properties": {
    "author": "qoqmarley",
    "publication_year": 2024,
    "external_link": "https://kyivindependent.com/news-feed/biden-putin-has-committed-war-crimes-charges-justified",
    "sentiment_score": "-0.296",
    "sentiment_label": "negative"
  }
}