{
  "title": "Are there good case studies of neural net interpretation leading to novel scientific theory/insight?",
  "backlink": "https://www.reddit.com/r/askscience/comments/vktwkx/are_there_good_case_studies_of_neural_net/",
  "language": "en",
  "classifications": [
    "reddit post"
  ],
  "properties": {
    "author": "Laddenvore",
    "publication_year": 2024,
    "external_link": "https://www.reddit.com/r/askscience/comments/vktwkx/are_there_good_case_studies_of_neural_net/",
    "sentiment_score": "0.9587",
    "sentiment_label": "very positive"
  }
}