{
  "title": "TIL: France still doesn't recognise North Korea, along with Japan and South Korea.",
  "backlink": "https://www.nknews.org/2014/01/frances-long-and-complicated-relationship-with-north-korea/",
  "language": "en",
  "classifications": [
    "reddit post"
  ],
  "properties": {
    "author": "eatandreddit",
    "publication_year": 2024,
    "external_link": "https://www.nknews.org/2014/01/frances-long-and-complicated-relationship-with-north-korea/",
    "sentiment_score": "0.0",
    "sentiment_label": "neutral"
  }
}