{
  "title": "AskScience AMA Series: I am Professor Kartik Hosanagar and I'm here to discuss how algorithms and AI control us and how we can control them. Ask Me Anything!",
  "backlink": "https://www.reddit.com/r/askscience/comments/b0knfu/askscience_ama_series_i_am_professor_kartik/",
  "language": "en",
  "classifications": [
    "reddit post"
  ],
  "properties": {
    "author": "AskScienceModerator",
    "publication_year": 2024,
    "external_link": "https://www.reddit.com/r/askscience/comments/b0knfu/askscience_ama_series_i_am_professor_kartik/",
    "sentiment_score": "0.2344",
    "sentiment_label": "positive"
  }
}