{
  "title": "If two major superpower created their own AI, what’s the most interesting scenario you imagine would happen when the AIs fight?",
  "backlink": "https://www.reddit.com/r/AskReddit/comments/17xtaz5/if_two_major_superpower_created_their_own_ai/",
  "language": "en",
  "classifications": [
    "reddit post"
  ],
  "properties": {
    "author": "HomerSimping",
    "publication_year": 2024,
    "external_link": "https://www.reddit.com/r/AskReddit/comments/17xtaz5/if_two_major_superpower_created_their_own_ai/",
    "sentiment_score": "0.3384",
    "sentiment_label": "positive"
  }
}