{
  "title": "What technique can be used to tell if an AI is truly intelligent?",
  "backlink": "https://www.reddit.com/r/askscience/comments/1u8jn8/what_technique_can_be_used_to_tell_if_an_ai_is/",
  "language": "en",
  "classifications": [
    "reddit post"
  ],
  "properties": {
    "author": "MonaLon",
    "publication_year": 2024,
    "external_link": "https://www.reddit.com/r/askscience/comments/1u8jn8/what_technique_can_be_used_to_tell_if_an_ai_is/",
    "sentiment_score": "0.807",
    "sentiment_label": "very positive"
  }
}