{
  "title": "TIL The 90s hit \"Macarena\" is actually about a woman named Macarena who cheats on her boyfriend with his two friends while he's being drafted into the army.",
  "backlink": "http://www.refinery29.com/2015/09/93452/macarena-song-meaning",
  "language": "en",
  "classifications": [
    "reddit post"
  ],
  "properties": {
    "author": "idoperach",
    "publication_year": 2024,
    "external_link": "http://www.refinery29.com/2015/09/93452/macarena-song-meaning",
    "sentiment_score": "0.0772",
    "sentiment_label": "slightly positive"
  }
}