{
  "title": "TIL that a Complete Fossil of 23 Million-Year-Old Lizard in Amber Resin was Found by Mexican Researchers",
  "backlink": "http://www.universityherald.com/articles/3813/20130709/complete-fossil-23-lizard-amber-resin-mexico.htm",
  "language": "en",
  "classifications": [
    "reddit post"
  ],
  "properties": {
    "author": "dnasuperior",
    "publication_year": 2024,
    "external_link": "http://www.universityherald.com/articles/3813/20130709/complete-fossil-23-lizard-amber-resin-mexico.htm",
    "sentiment_score": "0.0",
    "sentiment_label": "neutral"
  }
}