{
  "title": "TIL In 2006 Disney traded Al Michaels to Universal to regain the rights to Walt Disney's first character, Oswald the Rabbit",
  "backlink": "https://www.espn.com/nfl/story/_/id/12750497/how-espn-traded-al-michaels-oswald-rabbit",
  "language": "en",
  "classifications": [
    "reddit post"
  ],
  "properties": {
    "author": "NahumGardner",
    "publication_year": 2024,
    "external_link": "https://www.espn.com/nfl/story/_/id/12750497/how-espn-traded-al-michaels-oswald-rabbit",
    "sentiment_score": "0.0",
    "sentiment_label": "neutral"
  }
}